streamlit_perspective/__init__.py
streamlit_perspective/py.typed
streamlit_perspective-0.0.1.dist-info/WHEEL
streamlit_perspective-0.0.1.dist-info/METADATA
streamlit_perspective-0.0.1.dist-info/RECORD
