Metadata-Version: 2.3
Name: streamlit-perspective
Version: 0.0.1
Summary: Perspective components for Streamlit apps.
Author: Manuel Šarić
Author-email: Manuel Šarić <manujelko@gmail.com>
Requires-Python: >=3.10
